yakui/__init__.py
yakui/_callers.py
yakui/_constants.py
yakui/_levels.py
yakui/_loggers.py
yakui/_timestamps.py
yakui/ansi256/_beautify.py
yakui/ansi256/_colors.py
yakui/ansi256/_constants.py
yakui/ansi256/_effects.py
yakui/ansi256/_typehintings.py
yakui/ansi256/themes/_default.py
yakui/ansi256/themes/_theme.py
yakui-0.1.2.dist-info/LICENSE
yakui-0.1.2.dist-info/METADATA
yakui-0.1.2.dist-info/WHEEL
yakui-0.1.2.dist-info/RECORD
